chinese_characters_words/__init__.py
chinese_characters_words/交流.py
chinese_characters_words/字典.py
chinese_characters_words/字表.py
chinese_characters_words/结构解析.py
chinese_characters_words/词典.py
chinese_characters_words/语言.py
chinese_characters_words/跳过.txt
chinese_characters_words/数据/IDS-UCS-Basic.txt
chinese_characters_words/数据/__init__.py
chinese_characters_words/数据/字典.json
chinese_characters_words/数据/成语.json
chinese_characters_words-0.0.13.dist-info/METADATA
chinese_characters_words-0.0.13.dist-info/WHEEL
chinese_characters_words-0.0.13.dist-info/licenses/LICENSE
chinese_characters_words-0.0.13.dist-info/RECORD
