Metadata-Version: 2.3
Name: chinese_characters_words
Version: 0.0.13
Summary: 中文字词
Project-URL: Homepage, https://gitee.com/zhishi/chinese_characters_words
Project-URL: Bug Tracker, https://gitee.com/zhishi/chinese_characters_words/issues
Author-email: 吴烜 <nobodxbodon.github@gmail.com>
License-File: LICENSE
Classifier: License :: OSI Approved :: MIT License
Classifier: Operating System :: OS Independent
Classifier: Programming Language :: Python :: 3
Requires-Python: >=3.7
